typer_manifest/__init__.py
typer_manifest/collector.py
typer_manifest/core.py
typer_manifest/renderers.py
typer_manifest/types.py
typer_manifest-0.2.1.dist-info/METADATA
typer_manifest-0.2.1.dist-info/WHEEL
typer_manifest-0.2.1.dist-info/licenses/LICENSE
typer_manifest-0.2.1.dist-info/licenses/NOTICE
typer_manifest-0.2.1.dist-info/RECORD
