Metadata-Version: 2.4
Name: typer-manifest
Version: 0.2.1
Summary: Introspect Typer apps and export their full command manifest with pluggable renderers.
Project-URL: Homepage, https://github.com/cprima-forge/typer-manifest
Project-URL: Repository, https://github.com/cprima-forge/typer-manifest
Project-URL: Issues, https://github.com/cprima-forge/typer-manifest/issues
Project-URL: Documentation, https://github.com/cprima-forge/typer-manifest#readme
Project-URL: Changelog, https://github.com/cprima-forge/typer-manifest/blob/main/CHANGELOG.md
Author: Christian Prior-Mamulyan
License-Expression: Apache-2.0
License-File: LICENSE
License-File: NOTICE
Keywords: cli,click,command-line,documentation,introspection,manifest,testing,typer
Classifier: Development Status :: 4 - Beta
Classifier: Intended Audience :: Developers
Classifier: License :: OSI Approved :: Apache Software License
Classifier: Operating System :: OS Independent
Classifier: Programming Language :: Python :: 3
Classifier: Programming Language :: Python :: 3.10
Classifier: Programming Language :: Python :: 3.11
Classifier: Programming Language :: Python :: 3.12
Classifier: Programming Language :: Python :: 3.13
Classifier: Topic :: Software Development :: Documentation
Classifier: Topic :: Software Development :: Libraries :: Python Modules
Classifier: Topic :: System :: Shells
Classifier: Typing :: Typed
Requires-Python: >=3.10
Requires-Dist: click>=8.1
Requires-Dist: typer>=0.12
Provides-Extra: dev
Requires-Dist: black>=23.0; extra == 'dev'
Requires-Dist: mypy>=1.0; extra == 'dev'
Requires-Dist: pytest>=7.4; extra == 'dev'
Requires-Dist: ruff>=0.1; extra == 'dev'
